MANIFEST.in
README.md
readme.md
readme.rst
setup.py
seq2ftr/__init__.py
seq2ftr/adaptor.py
seq2ftr/feature_calculators.py
seq2ftr/test_feature_calculators.py
seq2ftr/transformer.py
seq2ftr.egg-info/PKG-INFO
seq2ftr.egg-info/SOURCES.txt
seq2ftr.egg-info/dependency_links.txt
seq2ftr.egg-info/requires.txt
seq2ftr.egg-info/top_level.txt