Metadata-Version: 1.1
Name: seq2ftr
Version: 0.1.7
Summary: A Nice and Convenient Feature Engineering Tool on Sequential Data
Home-page: https://github.com/smoothnlp/seq2ftr
Author: Ruinan(Victor) Zhang， YinJun(YJ)
Author-email: ruinan.zhang@icloud.com, yjun1989@gmail.com
License: UNKNOWN
Platform: UNKNOWN
Classifier: Programming Language :: Python :: 3
Classifier: License :: OSI Approved :: MIT License
Classifier: Operating System :: OS Independent
